{
  "generatedAt": "2026-05-14T08:00:50.708Z",
  "chain": "solana",
  "source": "Birdeye token_trending",
  "tokenCount": 20,
  "topNarrative": "Internet cult / Meme culture",
  "rotations": [
    {
      "id": "cult",
      "label": "Internet cult / Meme culture",
      "tokens": [
        {
          "address": "5UUH9RTDiSpq6HKS6bp4NdU9PNJpXRXuiw6ShBTBhgH2",
          "symbol": "TROLL",
          "name": "TROLL",
          "logoURI": "https://i.ibb.co/4gtJvGcG/image.png",
          "rank": 8,
          "price": 0.13020618217090127,
          "priceChange24h": 21.28330827799845,
          "volume24h": 14647690.50164634,
          "liquidity": 5234620.623103185,
          "fdv": 130060449.13377687,
          "matched": [
            "troll"
          ]
        },
        {
          "address": "21rKrtBzibPAZHAHQRzGiGDSh7XimCKB2a8VgsjZpump",
          "symbol": "CHUD",
          "name": "ChudTheBuilder",
          "logoURI": "https://ipfs.io/ipfs/QmcCfJCHfejmztjp1mPXsNv4DhEYGiScizhotrfMnJabSb",
          "rank": 5,
          "price": 0.0013563063973406411,
          "priceChange24h": 33.29670454193238,
          "volume24h": 4610310.568097429,
          "liquidity": 201305.7040239191,
          "fdv": 1356182.6848191116,
          "matched": [
            "chud"
          ]
        },
        {
          "address": "Ce2gx9KGXJ6C9Mp5b5x1sn9Mg87JwEbrQby4Zqo3pump",
          "symbol": "neet",
          "name": "NotInEmploymentEducationTraining",
          "logoURI": "https://ipfs.io/ipfs/QmXVKWN3i56vyh4Xot9sTb3XsCu92ihypcArFJLujuwzoS",
          "rank": 3,
          "price": 0.036588854243900855,
          "priceChange24h": 12.083206802871489,
          "volume24h": 2711534.1161672166,
          "liquidity": 2490280.3984655906,
          "fdv": 36580530.221473515,
          "matched": [
            "neet"
          ]
        },
        {
          "address": "3TYgKwkE2Y3rxdw9osLRSpxpXmSC1C1oo19W9KHspump",
          "symbol": "BULL",
          "name": "Bull",
          "logoURI": "https://pbs.twimg.com/profile_images/2042216772326019072/htTxm1_I_400x400.jpg",
          "rank": 13,
          "price": 0.0064824176540168,
          "priceChange24h": 17.16998866348878,
          "volume24h": 2061712.3219104838,
          "liquidity": 631186.9896091569,
          "fdv": 6482050.263753814,
          "matched": [
            "bull"
          ]
        },
        {
          "address": "8J69rbLTzWWgUJziFY8jeu5tDwEPBwUz4pKBMr5rpump",
          "symbol": "WOJAK",
          "name": "Wojak ",
          "logoURI": "https://ipfs.io/ipfs/bafkreighazhzw7kijsyhff77vvjgwbeonhq7fua7lpic4df7qjcajiykcm",
          "rank": 9,
          "price": 0.008534310968640947,
          "priceChange24h": 12.144503751910293,
          "volume24h": 1886720.3938498811,
          "liquidity": 924399.958602413,
          "fdv": 8533337.940946506,
          "matched": [
            "wojak"
          ]
        }
      ],
      "matchedTerms": [
        "bull",
        "chud",
        "neet",
        "troll",
        "wojak"
      ],
      "count": 5,
      "avgChange24h": 19.19554240764028,
      "totalVolume24h": 25917967.90167135,
      "totalLiquidity": 9481793.673804265,
      "medianFdv": 8533337.940946506,
      "score": 206
    },
    {
      "id": "infra",
      "label": "Infra / DePIN",
      "tokens": [
        {
          "address": "Gekfj7SL2fVpTDxJZmeC46cTYxinjB6gkAnb6EGT6mnn",
          "symbol": "dzSOL",
          "name": "DoubleZero Staked SOL",
          "logoURI": "https://fn474du36qdxqh6szvejo72imufs4tcnskea73kg4jx53e5rarba.arweave.net/K3n-Dpv0B3gf0s1Il39IZQsuTE2SiA_tRuJv3ZOxBEI",
          "rank": 18,
          "price": 95.36144101120492,
          "priceChange24h": -4.6421956628891685,
          "volume24h": 66571491.981507786,
          "liquidity": 646507155.2256925,
          "fdv": 646414922.4651778,
          "matched": [
            "sol"
          ]
        },
        {
          "address": "he1iusmfkpAdwvxLNGV8Y1iSbj4rUy6yMhEA3fotn9A",
          "symbol": "hSOL",
          "name": "Helius Staked SOL",
          "logoURI": "https://raw.githubusercontent.com/igneous-labs/lst-offchain-metadata/master/hSOL/hSOL.png",
          "rank": 19,
          "price": 105.92604422216587,
          "priceChange24h": -4.372218602903459,
          "volume24h": 2705808.0504710795,
          "liquidity": 59610042.604478605,
          "fdv": 59640797.60361843,
          "matched": [
            "sol"
          ]
        },
        {
          "address": "FCZKwHd9Qn1EQj8fFuNLB8dupAWCoJJNePbMqyHhS77b",
          "symbol": "XYO",
          "name": "XY Oracle (Wormhole)",
          "logoURI": null,
          "rank": 6,
          "price": 0.004761803326448476,
          "priceChange24h": 22.667647838637343,
          "volume24h": 355816.93990347313,
          "liquidity": 208953.0211174975,
          "fdv": 212284.53514630988,
          "matched": [
            "oracle"
          ]
        }
      ],
      "matchedTerms": [
        "oracle",
        "sol"
      ],
      "count": 3,
      "avgChange24h": 4.551077857614906,
      "totalVolume24h": 69633116.97188234,
      "totalLiquidity": 706326150.8512886,
      "medianFdv": 59640797.60361843,
      "score": 164
    },
    {
      "id": "bluechip",
      "label": "Bluechip / Majors",
      "tokens": [
        {
          "address": "Gekfj7SL2fVpTDxJZmeC46cTYxinjB6gkAnb6EGT6mnn",
          "symbol": "dzSOL",
          "name": "DoubleZero Staked SOL",
          "logoURI": "https://fn474du36qdxqh6szvejo72imufs4tcnskea73kg4jx53e5rarba.arweave.net/K3n-Dpv0B3gf0s1Il39IZQsuTE2SiA_tRuJv3ZOxBEI",
          "rank": 18,
          "price": 95.36144101120492,
          "priceChange24h": -4.6421956628891685,
          "volume24h": 66571491.981507786,
          "liquidity": 646507155.2256925,
          "fdv": 646414922.4651778,
          "matched": [
            "sol"
          ]
        },
        {
          "address": "he1iusmfkpAdwvxLNGV8Y1iSbj4rUy6yMhEA3fotn9A",
          "symbol": "hSOL",
          "name": "Helius Staked SOL",
          "logoURI": "https://raw.githubusercontent.com/igneous-labs/lst-offchain-metadata/master/hSOL/hSOL.png",
          "rank": 19,
          "price": 105.92604422216587,
          "priceChange24h": -4.372218602903459,
          "volume24h": 2705808.0504710795,
          "liquidity": 59610042.604478605,
          "fdv": 59640797.60361843,
          "matched": [
            "sol"
          ]
        },
        {
          "address": "HfMbPyDdZH6QMaDDUokjYCkHxzjoGBMpgaUvpLWGbF5p",
          "symbol": "PBTC",
          "name": "Purple Bitcoin",
          "logoURI": "https://gateway.irys.xyz/sSkCiLfqIwenQhAwaM-Yjfct9U1AkQpzALh4zk4oaZ8",
          "rank": 11,
          "price": 0.5596338147425013,
          "priceChange24h": 8.25310806359241,
          "volume24h": 228101.96708898782,
          "liquidity": 520361.5846192331,
          "fdv": 10806433.37564141,
          "matched": [
            "bitcoin"
          ]
        }
      ],
      "matchedTerms": [
        "bitcoin",
        "sol"
      ],
      "count": 3,
      "avgChange24h": -0.25376873406673894,
      "totalVolume24h": 69505401.99906786,
      "totalLiquidity": 706637559.4147904,
      "medianFdv": 59640797.60361843,
      "score": 159
    },
    {
      "id": "other",
      "label": "Other / Unclassified",
      "tokens": [
        {
          "address": "7HFqP4aDKDypcb2nsciTMUWDyK3v3GTWS6eMfK8ZvwQb",
          "symbol": "👑",
          "name": "👑",
          "logoURI": "https://pump.mypinata.cloud/ipfs/QmUQB9PVYsSwdGpGj2Pvktc1tP2ir8kC6cdjiA7e7jBeAM",
          "rank": 7,
          "price": 0.00006979608272831157,
          "priceChange24h": 2399.3559579436137,
          "volume24h": 745423.2158143339,
          "liquidity": 21763.130366858477,
          "fdv": 69792.73923449207,
          "matched": []
        },
        {
          "address": "Ei1LoZLaGbt5r7k1P3v7RjGgsd7g3R6id9A8EQmY3t4b",
          "symbol": "RCSC",
          "name": "Reserve Currency of Socialcom",
          "logoURI": "https://pbs.twimg.com/profile_images/2047483317243858944/eauoG1Dx_400x400.jpg",
          "rank": 1,
          "price": 0.0000017423559679310307,
          "priceChange24h": 476.7447087621065,
          "volume24h": 1971658.2255359674,
          "liquidity": 137800.12615821115,
          "fdv": 174235.59679310306,
          "matched": []
        },
        {
          "address": "669g9YAKRgAzBYXLF4hAa1advjVsn2YPGEBNxaBppump",
          "symbol": "马一龙",
          "name": "Yilongma",
          "logoURI": "https://ipfs.io/ipfs/bafkreifl6ex3r55b6aeug5dululgyshexq7fd4257mzlnxi7gn6x5bgnjy",
          "rank": 10,
          "price": 0.000022760135709479172,
          "priceChange24h": 726.615939770305,
          "volume24h": 572762.2339193143,
          "liquidity": 12909.892507975897,
          "fdv": 22760.085890373284,
          "matched": []
        },
        {
          "address": "8GxLxKA8tf3h8JUkXFfP4dNyn6D2vvwyGif5wanRpump",
          "symbol": "MASCOTS",
          "name": "2026 World Cup Mascots",
          "logoURI": "https://ipfs.io/ipfs/QmcQmygZeb67WAsE3bH9KLGygb17hF6z64FF82heenba7e",
          "rank": 14,
          "price": 0.0003780073623994844,
          "priceChange24h": 102.40067722542277,
          "volume24h": 1153888.6153651138,
          "liquidity": 64522.950690409074,
          "fdv": 378001.9503739853,
          "matched": []
        },
        {
          "address": "BAe9FELdH5TVCbrqSbwF75HcA5rNUX62c8FpYfLZpump",
          "symbol": "perps",
          "name": "perps",
          "logoURI": "https://ipfs.io/ipfs/bafkreicazrk47dehwsyijalbsmd43igrhxs7a662nwmx45pv7ofirwctme",
          "rank": 16,
          "price": 0.00004572229726967661,
          "priceChange24h": 750.5373306958658,
          "volume24h": 445883.4123357227,
          "liquidity": 17437.642302619613,
          "fdv": 45715.93255239271,
          "matched": []
        },
        {
          "address": "4xCUgkuWmpk1gmrcT9PmmCPVY8kFnHKCsMoLsRrNSPL",
          "symbol": "pToken",
          "name": "Pinnochio Token",
          "logoURI": "https://ipfs.io/ipfs/bafkreibwt4qdlj6a6jhjb2qehaowtgx4id6nohpkbzd2rvrpvaesbr3kfu",
          "rank": 12,
          "price": 0.00007143703082168135,
          "priceChange24h": 95.45228040838549,
          "volume24h": 954978.6921918201,
          "liquidity": 59752.608279093605,
          "fdv": 71422.12230731745,
          "matched": []
        },
        {
          "address": "2Ratx2g4QLFWp1bhjofyPrdLaeeNpP6fSxjA7HLDKXHx",
          "symbol": "ROAF",
          "name": "Russian Oil Asset Fund",
          "logoURI": "https://roaf.mypinata.cloud/ipfs/QmSxgB2hS3dDvPu66SNF4YnDcfHX4WtohHqBcYkJbwWRSD",
          "rank": 15,
          "price": 7.190375085012081e-7,
          "priceChange24h": 267.7113740837373,
          "volume24h": 411752.1115000766,
          "liquidity": 72049.32149980834,
          "fdv": 71903.7508501208,
          "matched": []
        },
        {
          "address": "MMBiSxREjrwNMmdxuBgvW9crKZTS136qHbpgN4Hpump",
          "symbol": "ECONOMY",
          "name": "In this economy?",
          "logoURI": "https://ipfs.io/ipfs/bafkreib6wx6megbi7fezqt65imj6iy5qfxemipdtwcri4mazuj5qljxqe4",
          "rank": 20,
          "price": 0.000010703098997200878,
          "priceChange24h": 303.4974248350488,
          "volume24h": 375914.2490439937,
          "liquidity": 8742.63568011461,
          "fdv": 10703.097917992058,
          "matched": []
        },
        {
          "address": "cZre8VoFrUMwJLuPdpgGUxWBdfsfnUQCKYFQE4Apump",
          "symbol": "Azure",
          "name": "AzureArcFifth",
          "logoURI": "https://desperate-moccasin-minnow.myfilebase.com/ipfs/QmU3tLALrS9z2x8XmLaDbMMWRAT1KFTU81k4FFFwJ7jxoW",
          "rank": 17,
          "price": 0.00006112799487270058,
          "priceChange24h": 235.01213481275997,
          "volume24h": 129176.0585735529,
          "liquidity": 21465.56563692808,
          "fdv": 61109.234196378064,
          "matched": []
        },
        {
          "address": "UwU8RVXB69Y6Dcju6cN2Qef6fykkq6UUNpB15rZku6Z",
          "symbol": "UWU",
          "name": "Unicorn",
          "logoURI": "https://i.degencdn.com/ipfs/bafkreibivgcck3ig7bo4edrykpmsds2a7424oys2ldyj2vief6b5nayq7q",
          "rank": 2,
          "price": 0.00011639977534012738,
          "priceChange24h": 48.017716272718175,
          "volume24h": 60549.38198571933,
          "liquidity": 524642.4116128163,
          "fdv": 1757543.5074715244,
          "matched": []
        }
      ],
      "matchedTerms": [],
      "count": 10,
      "avgChange24h": 540.5345544809963,
      "totalVolume24h": 6821986.196265616,
      "totalLiquidity": 941086.2847348351,
      "medianFdv": 71422.12230731745,
      "score": 158
    },
    {
      "id": "cat",
      "label": "Cat memes",
      "tokens": [
        {
          "address": "5p87X6WvQPam2WVZaEw39gTLKfpp3HVREAfY12Nu3UH6",
          "symbol": "RKC",
          "name": "Red Kitten Crew",
          "logoURI": "https://ipfs.io/ipfs/bafybeifbpcfl5osxwd5qzdizvy2nbt3ilnkzoaf6c7e7xx25f7bvtsbd4e",
          "rank": 4,
          "price": 0.0000029749576881340677,
          "priceChange24h": 971.8908792840383,
          "volume24h": 1222318.3114097812,
          "liquidity": 147061.87455124312,
          "fdv": 297495.76881340676,
          "matched": [
            "kitten"
          ]
        }
      ],
      "matchedTerms": [
        "kitten"
      ],
      "count": 1,
      "avgChange24h": 971.8908792840383,
      "totalVolume24h": 1222318.3114097812,
      "totalLiquidity": 147061.87455124312,
      "medianFdv": 297495.76881340676,
      "score": 138
    }
  ]
}